README.md
setup.cfg
setup.py
stubs.py
pystubs.egg-info/PKG-INFO
pystubs.egg-info/SOURCES.txt
pystubs.egg-info/dependency_links.txt
pystubs.egg-info/top_level.txt