Metadata-Version: 2.1
Name: pystubs
Version: 2018.5.3
Summary: Dummy values for equality testing
Home-page: https://github.com/andreacorbellini/pystubs
Author: Andrea Corbellini
Author-email: corbellini.andrea@gmail.com
License: Public Domain
Platform: UNKNOWN
